Aplicacion_Ventas/__init__.py
Aplicacion_Ventas/descuentos.py
Aplicacion_Ventas/excepciones.py
Aplicacion_Ventas/gestor_de_ventas.py
Aplicacion_Ventas/impuestos.py
Aplicacion_Ventas/precios.py
Test_Unitario/__init__.py
Test_Unitario/test_aplicación_ventas.py
aplicacion_de_ventas-0.1.3.dist-info/licenses/License.txt
aplicacion_de_ventas-0.1.3.dist-info/METADATA
aplicacion_de_ventas-0.1.3.dist-info/WHEEL
aplicacion_de_ventas-0.1.3.dist-info/top_level.txt
aplicacion_de_ventas-0.1.3.dist-info/RECORD
