Metadata-Version: 2.4
Name: aplicacion_de_ventas
Version: 0.1.3
Summary: Paquete para gestionar ventas, precios, impuestos y descuentos
Home-page: https://github.com/tu_usuario/gestor_ventas
Author: Marcello Paolo Massucco Bustios
Author-email: marcello.mass@gmail.com
Classifier: Programming Language :: Python :: 3
Classifier: License :: OSI Approved :: MIT License
Classifier: Operating System :: OS Independent
Requires-Python: >3.6
License-File: License.txt
Dynamic: author
Dynamic: author-email
Dynamic: classifier
Dynamic: description
Dynamic: description-content-type
Dynamic: home-page
Dynamic: license-file
Dynamic: requires-python
Dynamic: summary
